{"type":"PR","pr":{"number":181,"head":"33c62d589fc706398c035586ee1c44693bd318ce"},"user":"Ilya Krasnov","status":"pending_publish","branch":"cms/post/2019-11-12-הקדמה-לחלק-השני-הטיות-נפוצות-בניתוח-נתונים","collection":"post","commitMessage":"Update Post “2019-11-12-הקדמה-לחלק-השני-הטיות-נפוצות-בניתוח-נתונים”","title":"הקדמה לפוסטים הבאים - הטיות נפוצות בניתוח נתונים","description":"No Description!","objects":{"entry":{"path":"_posts/2019-11-12-הקדמה-לחלק-השני-הטיות-נפוצות-בניתוח-נתונים.md","sha":"6a2dfb0d2766eb51fd93ba40606339079cfb1322"},"files":[]},"timeStamp":"2020-01-28T18:44:42.513Z","version":"1"}